JianshuResearchTools/__init__.py
JianshuResearchTools/article.py
JianshuResearchTools/assert_funcs.py
JianshuResearchTools/basic_apis.py
JianshuResearchTools/collection.py
JianshuResearchTools/convert.py
JianshuResearchTools/exceptions.py
JianshuResearchTools/headers.py
JianshuResearchTools/httpx_client.py
JianshuResearchTools/island.py
JianshuResearchTools/notebook.py
JianshuResearchTools/objects.py
JianshuResearchTools/rank.py
JianshuResearchTools/user.py
JianshuResearchTools/utils.py
README.md
jianshuresearchtools-2.11.0.dist-info/LICENSE
jianshuresearchtools-2.11.0.dist-info/METADATA
jianshuresearchtools-2.11.0.dist-info/WHEEL
jianshuresearchtools-2.11.0.dist-info/RECORD
