Metadata-Version: 2.1
Name: jianshuresearchtools
Version: 2.11.0
Summary: 科技赋能创作星辰
Home-page: https://github.com/FHU-yezi/JianshuResearchTools
License: MIT
Keywords: jianshu,SDK
Author: yezi
Author-email: yehaowei20060411@qq.com
Requires-Python: >=3.7,<4.0
Classifier: Development Status :: 5 - Production/Stable
Classifier: License :: OSI Approved :: MIT License
Classifier: Operating System :: OS Independent
Classifier: Programming Language :: Python :: 3
Classifier: Programming Language :: Python :: 3.7
Classifier: Programming Language :: Python :: 3.8
Classifier: Programming Language :: Python :: 3.9
Classifier: Programming Language :: Python :: 3.10
Classifier: Programming Language :: Python :: 3.11
Classifier: Programming Language :: Python :: 3
Classifier: Typing :: Typed
Provides-Extra: full
Provides-Extra: high-perf
Provides-Extra: md-convert
Requires-Dist: httpx[http2] (>=0.24.0,<0.25.0)
Requires-Dist: lxml (>=4.9.2,<5.0.0)
Requires-Dist: tomd (>=0.1.3,<0.2.0) ; extra == "md-convert" or extra == "full"
Requires-Dist: ujson (>=5.7.0,<6.0.0) ; extra == "high-perf" or extra == "full"
Project-URL: Repository, https://github.com/FHU-yezi/JianshuResearchTools
